Workbook

Sheet Board_Overview
A1: VeriFix (Team HyperX) — cfo.ai Board Overview & Telemetry-Linked Executive Summary
A3: Executive KPI (Formula-Linked to 24M_Main_Model & Assumptions) | B3: Month 1 (Launch) | C3: Month 6 | D3: Month 12 (Y1 Exit) | E3: Month 24 (Y2 Exit) | F3: Architectural & Telemetry Driver
A4: Active Paying Customers | B4: ='24M_Main_Model'!B6 | C4: ='24M_Main_Model'!G6 | D4: ='24M_Main_Model'!M6 | E4: ='24M_Main_Model'!Y6 | F4: Solo Pro ($49) + Team ($249) + Enterprise ($999)
A5: Monthly Verified Patch Runs | B5: ='24M_Main_Model'!B7 | C5: ='24M_Main_Model'!G7 | D5: ='24M_Main_Model'!M7 | E5: ='24M_Main_Model'!Y7 | F5: Each run verified by pytest + AWS Lambda us-east-1
A6: Monthly Recurring + Usage Revenue | B6: ='24M_Main_Model'!B10 | C6: ='24M_Main_Model'!G10 | D6: ='24M_Main_Model'!M10 | E6: ='24M_Main_Model'!Y10 | F6: Billed globally via Dodo Payments MoR
A7: Annualized Run-Rate Revenue (ARR) | B7: ='24M_Main_Model'!B11 | C7: ='24M_Main_Model'!G11 | D7: ='24M_Main_Model'!M11 | E7: ='24M_Main_Model'!Y11 | F7: 12x Monthly Recognized Revenue
A8: Total COGS (v2 Graph-Guarded) | B8: ='24M_Main_Model'!B15 | C8: ='24M_Main_Model'!G15 | D8: ='24M_Main_Model'!M15 | E8: ='24M_Main_Model'!Y15 | F8: Includes LLM tokens, AWS Lambda, Dodo 3.9% MoR
A9: Gross Profit ($) | B9: ='24M_Main_Model'!B16 | C9: ='24M_Main_Model'!G16 | D9: ='24M_Main_Model'!M16 | E9: ='24M_Main_Model'!Y16 | F9: Revenue minus direct LLM, sandbox & payment COGS
A10: Gross Margin (%) | B10: ='24M_Main_Model'!B17 | C10: ='24M_Main_Model'!G17 | D10: ='24M_Main_Model'!M17 | E10: ='24M_Main_Model'!Y17 | F10: +79.83% Enterprise COGS reduction via entire-graph
A11: EBITDA / Net Monthly Cash Flow | B11: ='24M_Main_Model'!B22 | C11: ='24M_Main_Model'!G22 | D11: ='24M_Main_Model'!M22 | E11: ='24M_Main_Model'!Y22 | F11: Crosses cash-flow break-even in Month 4
A12: Ending Cash Balance ($) | B12: ='24M_Main_Model'!B23 | C12: ='24M_Main_Model'!G23 | D12: ='24M_Main_Model'!M23 | E12: ='24M_Main_Model'!Y23 | F12: Starts with $150,000 reserve; never drops below $112k
A13: Monthly COGS Saved by entire-graph | B13: ='24M_Main_Model'!B25 | C13: ='24M_Main_Model'!G25 | D13: ='24M_Main_Model'!M25 | E13: ='24M_Main_Model'!Y25 | F13: Counterfactual v1 COGS minus v2 Graph-Guarded COGS
A16: Measured Neatlogs Telemetry Impact on Unit Economics (Experiment exp_0e3f5ca743)
A17: Metric | B17: v1 Baseline (Before Fix) | C17: v2 Graph-Guarded (After Fix) | D17: Formula Delta | E17: % Improvement | F17: Partner Tool Attribution
A18: Prompt Tokens per Run | B18: =Assumptions!C13 | C18: =Assumptions!C15 | D18: =C18-B18 | E18: =(C18-B18)/B18 | F18: entire-graph search/impact/neighbors
A19: Completion Tokens per Run | B19: =Assumptions!C14 | C19: =Assumptions!C16 | D19: =C19-B19 | E19: =(C19-B19)/B19 | F19: Bounded caller contract synthesis
A20: Total Tokens per Run | B20: =B18+B19 | C20: =C18+C19 | D20: =C20-B20 | E20: =(C20-B20)/B20 | F20: Neatlogs RETRIEVER + AGENT span audit
A21: Modeled Enterprise COGS / Run | B21: =Assumptions!C17 | C21: =Assumptions!C18 | D21: =C21-B21 | E21: =(C21-B21)/B21 | F21: cfo.ai Unit Economics Engine

Sheet Assumptions
A1: VeriFix (Team HyperX) — cfo.ai Deterministic Model Assumptions & Telemetry Drivers
A2: Parameter Code | B2: Driver / Assumption Name | C2: Value | D2: Unit / Format | E2: Telemetry / Market Grounding Source
A3: START_CASH | B3: Starting Seed / Founder Treasury Cash | C3: 150000 | D3: $#,##0 | E3: Initial pre-seed / founder capital reserve
A4: PRICE_SOLO | B4: Solo Pro Tier Price (Monthly) | C4: 49 | D4: $#,##0.00 | E4: Includes 100 verified patches/mo; $0.60 overage
A5: PRICE_TEAM | B5: Team Guarded Tier Price (Monthly) | C5: 249 | D5: $#,##0.00 | E5: Includes 600 verified patches/mo; $0.45 overage
A6: PRICE_ENT | B6: Enterprise VPC & Compliance Tier (Monthly) | C6: 999 | D6: $#,##0.00 | E6: Includes 3,000 verified patches/mo; $0.35 overage
A7: RUNS_SOLO | B7: Avg Monthly Remediation Runs per Solo Customer | C7: 82 | D7: #,##0 | E7: Measured developer bug-fix cadence (~4/workday)
A8: RUNS_TEAM | B8: Avg Monthly Remediation Runs per Team Customer | C8: 480 | D8: #,##0 | E8: 6-seat engineering squad active PR defect load
A9: RUNS_ENT | B9: Avg Monthly Remediation Runs per Enterprise Customer | C9: 2450 | D9: #,##0 | E9: Multi-repo CI/CD autonomous patch verification
A10: OVERAGE_RATE | B10: Blended Overage Price per Extra Verified Run | C10: 0.45 | D10: $#,##0.00 | E10: Usage-based overage billing via Dodo Payments meters
A11: DODO_MOR_PCT | B11: Dodo Payments Merchant-of-Record Fee % | C11: 0.039 | D11: 0.0% | E11: Global tax, VAT/GST & subscription compliance fee (3.9%)
A12: DODO_FIXED | B12: Dodo Payments Fixed Fee per Transaction | C12: 0.4 | D12: $#,##0.00 | E12: Per-invoice settlement fee
A13: V1_PROMPT_TOK | B13: v1 Baseline Prompt Tokens per Run (Unbounded) | C13: 26743 | D13: #,##0 | E13: Measured in Neatlogs trace exp_24aa3f2776 (Before fix)
A14: V1_COMP_TOK | B14: v1 Baseline Completion Tokens per Run | C14: 4350 | D14: #,##0 | E14: Measured in Neatlogs trace exp_24aa3f2776 (Before fix)
... A23: GTM_BASE | B23: Monthly PLG & Open-Source DevRel Marketing Spend | C23: 2200 | D23: $#,##0 | E23: GitHub Marketplace, #neatHack OSS bug-hunt campaigns

Sheet 24M_Main_Model
A1: VeriFix — 24-Month Deterministic Operating & Cash Flow Model (Main Scenario — Formula Driven)
A2: Line Item / Metric | B2: M1 | C2: M2 | D2: M3 | E2: M4 | F2: M5 | G2: M6 | H2: M7 | I2: M8 | J2: M9 | K2: M10 | L2: M11 | M2: M12 | N2: M13 | O2: M14 | P2: M15 | Q2: M16 | R2: M17 | S2: M18 | T2: M19 | U2: M20 | V2: M21 | W2: M22 | X2: M23 | Y2: M24
A3: Active Solo Pro Customers ($49/mo) | B3: 14 | C3: =ROUND(B3*1.16 + 6, 0) | D3: =ROUND(C3*1.16 + 6, 0) | E3: =ROUND(D3*1.16 + 6, 0) | F3: =ROUND(E3*1.16 + 6, 0) | G3: =ROUND(F3*1.16 + 6, 0) | H3: =ROUND(G3*1.16 + 6, 0) | I3: =ROUND(H3*1.16 + 6, 0) | J3: =ROUND(I3*1.16 + 6, 0) | ... Y3: =ROUND(X3*1.16 + 6, 0)
A4: Active Team Guarded Customers ($249/mo) | B4: 3 | C4: =ROUND(B4*1.14 + 2, 0) | D4: =ROUND(C4*1.14 + 2, 0) | E4: =ROUND(D4*1.14 + 2, 0) | F4: =ROUND(E4*1.14 + 2, 0) | G4: =ROUND(F4*1.14 + 2, 0) | H4: =ROUND(G4*1.14 + 2, 0) | I4: =ROUND(H4*1.14 + 2, 0) | J4: =ROUND(I4*1.14 + 2, 0) | ... Y4: =ROUND(X4*1.14 + 2, 0)
A5: Active Enterprise VPC Customers ($999/mo) | B5: 1 | C5: =B5 + IF(MOD(2,2)=0, 1, 0) | D5: =C5 + IF(MOD(3,2)=0, 1, 0) | E5: =D5 + IF(MOD(4,2)=0, 1, 0) | F5: =E5 + IF(MOD(5,2)=0, 1, 0) | G5: =F5 + IF(MOD(6,2)=0, 1, 0) | H5: =G5 + IF(MOD(7,2)=0, 1, 0) | I5: =H5 + IF(MOD(8,2)=0, 1, 0) | J5: =I5 + IF(MOD(9,2)=0, 1, 0) | K5: =J5 + IF(MOD(10,2)=0, 1, 0) | L5: =K5 + IF(MOD(11,2)=0, 1, 0) | M5: =L5 + IF(MOD(12,2)=0, 1, 0) | N5: =M5 + IF(MOD(13,2)=0, 1, 0) | O5: =N5 + IF(MOD(14,2)=0, 1, 0) | P5: =O5 + IF(MOD(15,2)=0, 1, 0) | Q5: =P5 + IF(MOD(16,2)=0, 1, 0) | R5: =Q5 + IF(MOD(17,2)=0, 1, 0) | S5: =R5 + IF(MOD(18,2)=0, 1, 0) | T5: =S5 + IF(MOD(19,2)=0, 1, 0) | U5: =T5 + IF(MOD(20,2)=0, 1, 0) | V5: =U5 + IF(MOD(21,2)=0, 1, 0) | W5: =V5 + IF(MOD(22,2)=0, 1, 0) | X5: =W5 + IF(MOD(23,2)=0, 1, 0) | Y5: =X5 + IF(MOD(24,2)=0, 1, 0)
A6: Total Active Customers | B6: =SUM(B3:B5) | C6: =SUM(C3:C5) | D6: =SUM(D3:D5) | E6: =SUM(E3:E5) | F6: =SUM(F3:F5) | G6: =SUM(G3:G5) | H6: =SUM(H3:H5) | I6: =SUM(I3:I5) | ... Y6: =SUM(Y3:Y5)
A7: Total Monthly Verified Remediation Runs | B7: =B3*Assumptions!$C$7 + B4*Assumptions!$C$8 + B5*Assumptions!$C$9 | C7: =C3*Assumptions!$C$7 + C4*Assumptions!$C$8 + C5*Assumptions!$C$9 | D7: =D3*Assumptions!$C$7 + D4*Assumptions!$C$8 + D5*Assumptions!$C$9 | E7: =E3*Assumptions!$C$7 + E4*Assumptions!$C$8 + E5*Assumptions!$C$9 | F7: =F3*Assumptions!$C$7 + F4*Assumptions!$C$8 + F5*Assumptions!$C$9 | G7: =G3*Assumptions!$C$7 + G4*Assumptions!$C$8 + G5*Assumptions!$C$9 | H7: =H3*Assumptions!$C$7 + H4*Assumptions!$C$8 + H5*Assumptions!$C$9 | I7: =I3*Assumptions!$C$7 + I4*Assumptions!$C$8 + I5*Assumptions!$C$9 | ... Y7: =Y3*Assumptions!$C$7 + Y4*Assumptions!$C$8 + Y5*Assumptions!$C$9
A8: Subscription MRR ($) | B8: =B3*Assumptions!$C$4 + B4*Assumptions!$C$5 + B5*Assumptions!$C$6 | C8: =C3*Assumptions!$C$4 + C4*Assumptions!$C$5 + C5*Assumptions!$C$6 | D8: =D3*Assumptions!$C$4 + D4*Assumptions!$C$5 + D5*Assumptions!$C$6 | E8: =E3*Assumptions!$C$4 + E4*Assumptions!$C$5 + E5*Assumptions!$C$6 | F8: =F3*Assumptions!$C$4 + F4*Assumptions!$C$5 + F5*Assumptions!$C$6 | G8: =G3*Assumptions!$C$4 + G4*Assumptions!$C$5 + G5*Assumptions!$C$6 | H8: =H3*Assumptions!$C$4 + H4*Assumptions!$C$5 + H5*Assumptions!$C$6 | I8: =I3*Assumptions!$C$4 + I4*Assumptions!$C$5 + I5*Assumptions!$C$6 | ... Y8: =Y3*Assumptions!$C$4 + Y4*Assumptions!$C$5 + Y5*Assumptions!$C$6
A9: Usage Overage Revenue ($) | B9: =ROUND(B7*0.12*Assumptions!$C$10, 2) | C9: =ROUND(C7*0.12*Assumptions!$C$10, 2) | D9: =ROUND(D7*0.12*Assumptions!$C$10, 2) | E9: =ROUND(E7*0.12*Assumptions!$C$10, 2) | F9: =ROUND(F7*0.12*Assumptions!$C$10, 2) | G9: =ROUND(G7*0.12*Assumptions!$C$10, 2) | H9: =ROUND(H7*0.12*Assumptions!$C$10, 2) | I9: =ROUND(I7*0.12*Assumptions!$C$10, 2) | ... Y9: =ROUND(Y7*0.12*Assumptions!$C$10, 2)
A10: Total Gross Monthly Revenue (MRR + Usage) | B10: =B8+B9 | C10: =C8+C9 | D10: =D8+D9 | E10: =E8+E9 | F10: =F8+F9 | G10: =G8+G9 | H10: =H8+H9 | I10: =I8+I9 | ... Y10: =Y8+Y9
A11: Annualized Run-Rate Revenue (ARR) | B11: =B10*12 | C11: =C10*12 | D11: =D10*12 | E11: =E10*12 | F11: =F10*12 | G11: =G10*12 | H11: =H10*12 | I11: =I10*12 | ... Y11: =Y10*12
A12: LLM & entire-graph Compute COGS (v2 Guarded) | B12: =ROUND(B7*(0.35*Assumptions!$C$18 + 0.65*Assumptions!$C$19), 2) | C12: =ROUND(C7*(0.35*Assumptions!$C$18 + 0.65*Assumptions!$C$19), 2) | D12: =ROUND(D7*(0.35*Assumptions!$C$18 + 0.65*Assumptions!$C$19), 2) | E12: =ROUND(E7*(0.35*Assumptions!$C$18 + 0.65*Assumptions!$C$19), 2) | F12: =ROUND(F7*(0.35*Assumptions!$C$18 + 0.65*Assumptions!$C$19), 2) | G12: =ROUND(G7*(0.35*Assumptions!$C$18 + 0.65*Assumptions!$C$19), 2) | H12: =ROUND(H7*(0.35*Assumptions!$C$18 + 0.65*Assumptions!$C$19), 2) | I12: =ROUND(I7*(0.35*Assumptions!$C$18 + 0.65*Assumptions!$C$19), 2) | ... Y12: =ROUND(Y7*(0.35*Assumptions!$C$18 + 0.65*Assumptions!$C$19), 2)
A13: AWS Lambda Attestation & Worktree Sandbox COGS | B13: =ROUND(B7*(Assumptions!$C$20 + 0.002), 2) | C13: =ROUND(C7*(Assumptions!$C$20 + 0.002), 2) | D13: =ROUND(D7*(Assumptions!$C$20 + 0.002), 2) | E13: =ROUND(E7*(Assumptions!$C$20 + 0.002), 2) | F13: =ROUND(F7*(Assumptions!$C$20 + 0.002), 2) | G13: =ROUND(G7*(Assumptions!$C$20 + 0.002), 2) | H13: =ROUND(H7*(Assumptions!$C$20 + 0.002), 2) | I13: =ROUND(I7*(Assumptions!$C$20 + 0.002), 2) | ... Y13: =ROUND(Y7*(Assumptions!$C$20 + 0.002), 2)
A14: Dodo Payments Merchant-of-Record Fees (3.9% + $0.40) | B14: =ROUND(B10*Assumptions!$C$11 + B6*Assumptions!$C$12, 2) | C14: =ROUND(C10*Assumptions!$C$11 + C6*Assumptions!$C$12, 2) | D14: =ROUND(D10*Assumptions!$C$11 + D6*Assumptions!$C$12, 2) | E14: =ROUND(E10*Assumptions!$C$11 + E6*Assumptions!$C$12, 2) | F14: =ROUND(F10*Assumptions!$C$11 + F6*Assumptions!$C$12, 2) | G14: =ROUND(G10*Assumptions!$C$11 + G6*Assumptions!$C$12, 2) | H14: =ROUND(H10*Assumptions!$C$11 + H6*Assumptions!$C$12, 2) | I14: =ROUND(I10*Assumptions!$C$11 + I6*Assumptions!$C$12, 2) | ... Y14: =ROUND(Y10*Assumptions!$C$11 + Y6*Assumptions!$C$12, 2)
A15: Total Cost of Goods Sold (COGS) | B15: =SUM(B12:B14) | C15: =SUM(C12:C14) | D15: =SUM(D12:D14) | E15: =SUM(E12:E14) | F15: =SUM(F12:F14) | G15: =SUM(G12:G14) | H15: =SUM(H12:H14) | I15: =SUM(I12:I14) | ... Y15: =SUM(Y12:Y14)
A16: Gross Profit ($) | B16: =B10-B15 | C16: =C10-C15 | D16: =D10-D15 | E16: =E10-E15 | F16: =F10-F15 | G16: =G10-G15 | H16: =H10-H15 | I16: =I10-I15 | ... Y16: =Y10-Y15
A17: Gross Margin (%) | B17: =IF(B10>0, B16/B10, 0) | C17: =IF(C10>0, C16/C10, 0) | D17: =IF(D10>0, D16/D10, 0) | E17: =IF(E10>0, E16/E10, 0) | F17: =IF(F10>0, F16/F10, 0) | G17: =IF(G10>0, G16/G10, 0) | H17: =IF(H10>0, H16/H10, 0) | I17: =IF(I10>0, I16/I10, 0) | ... Y17: =IF(Y10>0, Y16/Y10, 0)
A18: Core Engineering & Operations Payroll | B18: =Assumptions!$C$21 + IF(1>6, 6500, 0) + IF(1>12, 9000, 0) + IF(1>18, 12000, 0) | C18: =Assumptions!$C$21 + IF(2>6, 6500, 0) + IF(2>12, 9000, 0) + IF(2>18, 12000, 0) | D18: =Assumptions!$C$21 + IF(3>6, 6500, 0) + IF(3>12, 9000, 0) + IF(3>18, 12000, 0) | E18: =Assumptions!$C$21 + IF(4>6, 6500, 0) + IF(4>12, 9000, 0) + IF(4>18, 12000, 0) | F18: =Assumptions!$C$21 + IF(5>6, 6500, 0) + IF(5>12, 9000, 0) + IF(5>18, 12000, 0) | G18: =Assumptions!$C$21 + IF(6>6, 6500, 0) + IF(6>12, 9000, 0) + IF(6>18, 12000, 0) | H18: =Assumptions!$C$21 + IF(7>6, 6500, 0) + IF(7>12, 9000, 0) + IF(7>18, 12000, 0) | I18: =Assumptions!$C$21 + IF(8>6, 6500, 0) + IF(8>12, 9000, 0) + IF(8>18, 12000, 0) | J18: =Assumptions!$C$21 + IF(9>6, 6500, 0) + IF(9>12, 9000, 0) + IF(9>18, 12000, 0) | K18: =Assumptions!$C$21 + IF(10>6, 6500, 0) + IF(10>12, 9000, 0) + IF(10>18, 12000, 0) | L18: =Assumptions!$C$21 + IF(11>6, 6500, 0) + IF(11>12, 9000, 0) + IF(11>18, 12000, 0) | M18: =Assumptions!$C$21 + IF(12>6, 6500, 0) + IF(12>12, 9000, 0) + IF(12>18, 12000, 0) | N18: =Assumptions!$C$21 + IF(13>6, 6500, 0) + IF(13>12, 9000, 0) + IF(13>18, 12000, 0) | O18: =Assumptions!$C$21 + IF(14>6, 6500, 0) + IF(14>12, 9000, 0) + IF(14>18, 12000, 0) | P18: =Assumptions!$C$21 + IF(15>6, 6500, 0) + IF(15>12, 9000, 0) + IF(15>18, 12000, 0) | Q18: =Assumptions!$C$21 + IF(16>6, 6500, 0) + IF(16>12, 9000, 0) + IF(16>18, 12000, 0) | R18: =Assumptions!$C$21 + IF(17>6, 6500, 0) + IF(17>12, 9000, 0) + IF(17>18, 12000, 0) | S18: =Assumptions!$C$21 + IF(18>6, 6500, 0) + IF(18>12, 9000, 0) + IF(18>18, 12000, 0) | T18: =Assumptions!$C$21 + IF(19>6, 6500, 0) + IF(19>12, 9000, 0) + IF(19>18, 12000, 0) | U18: =Assumptions!$C$21 + IF(20>6, 6500, 0) + IF(20>12, 9000, 0) + IF(20>18, 12000, 0) | V18: =Assumptions!$C$21 + IF(21>6, 6500, 0) + IF(21>12, 9000, 0) + IF(21>18, 12000, 0) | W18: =Assumptions!$C$21 + IF(22>6, 6500, 0) + IF(22>12, 9000, 0) + IF(22>18, 12000, 0) | X18: =Assumptions!$C$21 + IF(23>6, 6500, 0) + IF(23>12, 9000, 0) + IF(23>18, 12000, 0) | Y18: =Assumptions!$C$21 + IF(24>6, 6500, 0) + IF(24>12, 9000, 0) + IF(24>18, 12000, 0)
A19: Fixed Cloud, Neatlogs Pro & Entire Infrastructure | B19: =Assumptions!$C$22 + ROUND(B6*4.5, 0) | C19: =Assumptions!$C$22 + ROUND(C6*4.5, 0) | D19: =Assumptions!$C$22 + ROUND(D6*4.5, 0) | E19: =Assumptions!$C$22 + ROUND(E6*4.5, 0) | F19: =Assumptions!$C$22 + ROUND(F6*4.5, 0) | G19: =Assumptions!$C$22 + ROUND(G6*4.5, 0) | H19: =Assumptions!$C$22 + ROUND(H6*4.5, 0) | I19: =Assumptions!$C$22 + ROUND(I6*4.5, 0) | ... Y19: =Assumptions!$C$22 + ROUND(Y6*4.5, 0)
A20: PLG, DevRel & Open-Source Growth Marketing | B20: =Assumptions!$C$23 + ROUND(B10*0.08, 0) | C20: =Assumptions!$C$23 + ROUND(C10*0.08, 0) | D20: =Assumptions!$C$23 + ROUND(D10*0.08, 0) | E20: =Assumptions!$C$23 + ROUND(E10*0.08, 0) | F20: =Assumptions!$C$23 + ROUND(F10*0.08, 0) | G20: =Assumptions!$C$23 + ROUND(G10*0.08, 0) | H20: =Assumptions!$C$23 + ROUND(H10*0.08, 0) | I20: =Assumptions!$C$23 + ROUND(I10*0.08, 0) | ... Y20: =Assumptions!$C$23 + ROUND(Y10*0.08, 0)
A21: Total Operating Expenses (OpEx) | B21: =SUM(B18:B20) | C21: =SUM(C18:C20) | D21: =SUM(D18:D20) | E21: =SUM(E18:E20) | F21: =SUM(F18:F20) | G21: =SUM(G18:G20) | H21: =SUM(H18:H20) | I21: =SUM(I18:I20) | ... Y21: =SUM(Y18:Y20)
A22: EBITDA / Net Monthly Operating Cash Flow | B22: =B16-B21 | C22: =C16-C21 | D22: =D16-D21 | E22: =E16-E21 | F22: =F16-F21 | G22: =G16-G21 | H22: =H16-H21 | I22: =I16-I21 | ... Y22: =Y16-Y21
A23: Ending Cash Balance ($) | B23: =Assumptions!$C$3+B22 | C23: =B23+C22 | D23: =C23+D22 | E23: =D23+E22 | F23: =E23+F22 | G23: =F23+G22 | H23: =G23+H22 | I23: =H23+I22 | J23: =I23+J22 | ... Y23: =X23+Y22
A24: Counterfactual v1 Unoptimized COGS (Without entire-graph) | B24: =ROUND(B7*(0.35*Assumptions!$C$17 + 0.65*(Assumptions!$C$19*2.95)), 2) | C24: =ROUND(C7*(0.35*Assumptions!$C$17 + 0.65*(Assumptions!$C$19*2.95)), 2) | D24: =ROUND(D7*(0.35*Assumptions!$C$17 + 0.65*(Assumptions!$C$19*2.95)), 2) | E24: =ROUND(E7*(0.35*Assumptions!$C$17 + 0.65*(Assumptions!$C$19*2.95)), 2) | F24: =ROUND(F7*(0.35*Assumptions!$C$17 + 0.65*(Assumptions!$C$19*2.95)), 2) | G24: =ROUND(G7*(0.35*Assumptions!$C$17 + 0.65*(Assumptions!$C$19*2.95)), 2) | H24: =ROUND(H7*(0.35*Assumptions!$C$17 + 0.65*(Assumptions!$C$19*2.95)), 2) | I24: =ROUND(I7*(0.35*Assumptions!$C$17 + 0.65*(Assumptions!$C$19*2.95)), 2) | ... Y24: =ROUND(Y7*(0.35*Assumptions!$C$17 + 0.65*(Assumptions!$C$19*2.95)), 2)
A25: Monthly Direct COGS Saved by entire-graph + Neatlogs | B25: =B24-B12 | C25: =C24-C12 | D25: =D24-D12 | E25: =E24-E12 | F25: =F24-F12 | G25: =G24-G12 | H25: =H24-H12 | I25: =I24-I12 | ... Y25: =Y24-Y12

Sheet 4Q_Scenario_Comparison
A1: VeriFix — 4-Quarter Multi-Scenario Financial Comparison (Main vs. Growth vs. Downside)
A2: Scenario | B2: Quarter | C2: Active Customers | D2: Total Runs | E2: Recognized Revenue ($) | F2: Total COGS ($) | G2: Gross Margin (%) | H2: EBITDA ($) | I2: Ending Cash ($)
A3: Main (Graph-Optimized Base Plan) | B3: Q1 (Oct–Dec 2026) | C3: 18 | D3: 14550 | E3: 20728.5 | F3: 2214.62 | G3: =(E3-F3)/E3 | H3: 2013.88 | I3: 27013.88
A4: Main (Graph-Optimized Base Plan) | B4: Q2 (Jan–Mar 2027) | C4: 46 | D4: 40956 | E4: 57606 | F4: 6643.75 | G4: =(E4-F4)/E4 | H4: 22462.25 | I4: 49476.13
A5: Main (Graph-Optimized Base Plan) | B5: Q3 (Apr–Jun 2027) | C5: 88 | D5: 80565 | E5: 112922.25 | F5: 10587.45 | G5: =(E5-F5)/E5 | H5: 54334.8 | I5: 103810.93
A6: Main (Graph-Optimized Base Plan) | B6: Q4 (Jul–Sep 2027) | C6: 145 | D6: 137958 | E6: 192462 | F6: 16277.93 | G6: =(E6-F6)/E6 | H6: 104184.07 | I6: 207995
A7: Growth (Ecosystem Attach Upside) | B7: Q1 (Oct–Dec 2026) | C7: 29 | D7: 22824 | E7: 32716.5 | F7: 2900.1 | G7: =(E7-F7)/E7 | H7: 10841.4 | I7: 35841.4
A8: Growth (Ecosystem Attach Upside) | B8: Q2 (Jan–Mar 2027) | C8: 76 | D8: 67710 | E8: 95149.5 | F8: 8854.12 | G8: =(E8-F8)/E8 | H8: 53520.38 | I8: 89361.78
A9: Growth (Ecosystem Attach Upside) | B9: Q3 (Apr–Jun 2027) | C9: 145 | D9: 133551 | E9: 187010.25 | F9: 14958.4 | G9: =(E9-F9)/E9 | H9: 116851.85 | I9: 206213.63
A10: Growth (Ecosystem Attach Upside) | B10: Q4 (Jul–Sep 2027) | C10: 240 | D10: 229206 | E10: 319576.5 | F10: 23792.07 | G10: =(E10-F10)/E10 | H10: 212984.43 | I10: 419198.06
A11: Downside (Unoptimized Grep + High Retry Burn) | B11: Q1 (Oct–Dec 2026) | C11: 14 | D11: 26359 | E11: 17481 | F11: 50528.03 | G11: =(E11-F11)/E11 | H11: -49547.03 | I11: -24547.03
A12: Downside (Unoptimized Grep + High Retry Burn) | B12: Q2 (Jan–Mar 2027) | C12: 34 | D12: 60379 | E12: 40791 | F12: 116602.78 | G12: =(E12-F12)/E12 | H12: -104311.78 | I12: -128858.81
A13: Downside (Unoptimized Grep + High Retry Burn) | B13: Q3 (Apr–Jun 2027) | C13: 66 | D13: 126548 | E13: 84452.25 | F13: 241551.94 | G13: =(E13-F13)/E13 | H13: -205099.69 | I13: -333958.5
A14: Downside (Unoptimized Grep + High Retry Burn) | B14: Q4 (Jul–Sep 2027) | C14: 109 | D14: 219347 | E14: 145553.25 | F14: 416782.3 | G14: =(E14-F14)/E14 | H14: -343229.05 | I14: -677187.55
